Metadata-Version: 2.1
Name: harvest-cropper
Version: 0.0.3
Summary: An app to explore Harvest data
Home-page: https://github.com/CartoDB/cropper
Author: Jorge Sanz
Author-email: jsanz@carto.com
License: BSD
Keywords: harvest api
Platform: UNKNOWN
Classifier: License :: OSI Approved :: BSD License
Classifier: Programming Language :: Python :: 3
Classifier: Programming Language :: Python :: 3.7
